beacon_client/api.py
beacon_client/beacon_endpoints.py
beacon_client/config_endpoints.py
beacon_client/debug_endpoints.py
beacon_client/event_endpoints.py
beacon_client/node_endpoints.py
beacon_client/utils/parsing.py
beacon_client/utils/types.py
beacon_client/validator_endpoints.py
beacon_client_py-0.2.0.dist-info/LICENSE
beacon_client_py-0.2.0.dist-info/WHEEL
beacon_client_py-0.2.0.dist-info/METADATA
beacon_client_py-0.2.0.dist-info/RECORD
