Metadata-Version: 2.1
Name: beacon-client-py
Version: 0.2.0
Summary: A Python Client for interacting with the Ethereum Beacon Chain API
Author: Benedict Brady
Requires-Python: >=3.10,<4.0
Classifier: Programming Language :: Python :: 3
Classifier: Programming Language :: Python :: 3.10
Classifier: Programming Language :: Python :: 3.11
Requires-Dist: bitstring (>=3.1.9,<4.0.0)
Requires-Dist: dacite (>=1.6.0,<2.0.0)
Requires-Dist: multiaddr (>=0.0.9,<0.0.10)
Requires-Dist: requests (>=2.28.1,<3.0.0)
Requires-Dist: sseclient-py (>=1.7.2,<2.0.0)
